warehouse_core/__init__.py
warehouse_core/db/__init__.py
warehouse_core/db/connection.py
warehouse_core/db/ibis_connection.py
warehouse_core/db/manager.py
warehouse_core/engine/__init__.py
warehouse_core/engine/job_base.py
warehouse_core/utils/__init__.py
warehouse_core/utils/logger.py
warehouse_core-0.1.1.dist-info/METADATA
warehouse_core-0.1.1.dist-info/WHEEL
warehouse_core-0.1.1.dist-info/RECORD
