Metadata-Version: 2.1
Name: warehouse-core
Version: 0.1.1
Summary: 数据处理核心库，提供数据库连接和Ibis数据处理能力
License: MIT
Author: Zeng Kaishin
Author-email: kaishinz@qq.com
Requires-Python: >=3.11,<4.0
Classifier: License :: OSI Approved :: MIT License
Classifier: Programming Language :: Python :: 3
Classifier: Programming Language :: Python :: 3.11
Requires-Dist: ibis-framework[mysql,pyspark,sqlite] (>=9.0.0,<10.0.0)
Requires-Dist: pandas (>=2.0.0,<3.0.0)
Requires-Dist: pyyaml (>=6.0,<7.0)
Requires-Dist: sqlalchemy (>=2.0.0,<3.0.0)
